ESRNN/ESRNN.py
ESRNN/ESRNNensemble.py
ESRNN/M4_data.py
ESRNN/__init__.py
ESRNN/hyperpar_tunning_m4.py
ESRNN/m4_data.py
ESRNN/m4_run.py
ESRNN/utils_configs.py
ESRNN/utils_datetime.py
ESRNN/utils_evaluation.py
ESRNN/utils_visualization.py
ESRNN/utils/DRNN.py
ESRNN/utils/ESRNN.py
ESRNN/utils/__init__.py
ESRNN/utils/config.py
ESRNN/utils/data.py
ESRNN/utils/losses.py
ESRNN-0.1.3.dist-info/LICENSE
ESRNN-0.1.3.dist-info/METADATA
ESRNN-0.1.3.dist-info/WHEEL
ESRNN-0.1.3.dist-info/entry_points.txt
ESRNN-0.1.3.dist-info/top_level.txt
ESRNN-0.1.3.dist-info/RECORD
