Metadata-Version: 2.1
Name: ESRNN
Version: 0.1.3
Summary: Pytorch implementation of the ESRNN
Home-page: https://github.com/kdgutier/esrnn_torch
Author: Kin Gutierrez, Cristian Challu, Federico Garza
Author-email: kdgutier@cs.cmu.edu, cchallu@andrew.cmu.edu, fede.garza.ramirez@gmail.com
License: UNKNOWN
Platform: UNKNOWN
Classifier: Programming Language :: Python :: 3
Classifier: License :: OSI Approved :: MIT License
Classifier: Operating System :: OS Independent
Requires-Python: >=3.6
Requires-Dist: numpy (>=1.16.1)
Requires-Dist: pandas (>=0.25.2)
Requires-Dist: torch (>=1.3.1)
